odoo/addons/fetchmail_notify_error_to_sender/README.rst
odoo/addons/fetchmail_notify_error_to_sender/__init__.py
odoo/addons/fetchmail_notify_error_to_sender/__manifest__.py
odoo/addons/fetchmail_notify_error_to_sender/data/email_template_data.xml
odoo/addons/fetchmail_notify_error_to_sender/i18n/ca.po
odoo/addons/fetchmail_notify_error_to_sender/i18n/de.po
odoo/addons/fetchmail_notify_error_to_sender/i18n/es.po
odoo/addons/fetchmail_notify_error_to_sender/i18n/fetchmail_notify_error_to_sender.pot
odoo/addons/fetchmail_notify_error_to_sender/i18n/fr.po
odoo/addons/fetchmail_notify_error_to_sender/i18n/hr.po
odoo/addons/fetchmail_notify_error_to_sender/i18n/it.po
odoo/addons/fetchmail_notify_error_to_sender/i18n/pt_BR.po
odoo/addons/fetchmail_notify_error_to_sender/i18n/pt_PT.po
odoo/addons/fetchmail_notify_error_to_sender/i18n/sl.po
odoo/addons/fetchmail_notify_error_to_sender/i18n/tr.po
odoo/addons/fetchmail_notify_error_to_sender/i18n/zh_CN.po
odoo/addons/fetchmail_notify_error_to_sender/models/__init__.py
odoo/addons/fetchmail_notify_error_to_sender/models/fetchmail.py
odoo/addons/fetchmail_notify_error_to_sender/models/mail_thread.py
odoo/addons/fetchmail_notify_error_to_sender/readme/CONFIGURE.rst
odoo/addons/fetchmail_notify_error_to_sender/readme/CONTRIBUTORS.rst
odoo/addons/fetchmail_notify_error_to_sender/readme/DESCRIPTION.rst
odoo/addons/fetchmail_notify_error_to_sender/static/description/icon.png
odoo/addons/fetchmail_notify_error_to_sender/static/description/index.html
odoo/addons/fetchmail_notify_error_to_sender/views/fetchmail_view.xml
odoo13_addon_fetchmail_notify_error_to_sender-13.0.2.0.1.dist-info/METADATA
odoo13_addon_fetchmail_notify_error_to_sender-13.0.2.0.1.dist-info/WHEEL
odoo13_addon_fetchmail_notify_error_to_sender-13.0.2.0.1.dist-info/top_level.txt
odoo13_addon_fetchmail_notify_error_to_sender-13.0.2.0.1.dist-info/RECORD
