Metadata-Version: 2.1
Name: odoo13-addon-fetchmail-notify-error-to-sender
Version: 13.0.2.0.1
Summary: If fetching mails gives error, send an email to sender
Home-page: https://github.com/OCA/server-tools
Author: Agile Business Group,ForgeFlow,Odoo Community Association (OCA)
Author-email: support@odoo-community.org
License: AGPL-3
Platform: UNKNOWN
Classifier: Programming Language :: Python
Classifier: Framework :: Odoo
Classifier: Framework :: Odoo :: 13.0
Classifier: License :: OSI Approved :: GNU Affero General Public License v3
Requires-Python: >=3.5
Requires-Dist: odoo (<13.1dev,>=13.0a)
